umbreon/bot.py
umbreon/cogs/error.py
umbreon/cogs/example.py
umbreon/cogs/fun.py
umbreon/cogs/help.py
umbreon/cogs/moderation.py
umbreon-0.1.0.dist-info/LICENSE
umbreon-0.1.0.dist-info/WHEEL
umbreon-0.1.0.dist-info/METADATA
umbreon-0.1.0.dist-info/RECORD
